{"cameraMode":{"drawMode":0,"name":"Shaded","section":"Shading Mode"},"sceneLighting":false,"audioPlay":false,"sceneViewState":{"showFog":true,"showMaterialUpdate":false,"showSkybox":false,"showFlares":true,"showImageEffects":true,"showParticleSystems":true,"showVisualEffectGraphs":true,"m_FxEnabled":true},"in2DMode":false,"pivot":{"x":155.016357421875,"y":-588.3199462890625,"z":-2075.4912109375},"rotation":{"x":0.165130153298378,"y":0.30540236830711367,"z":-0.05396512895822525,"w":0.9363036155700684},"size":1968.27197265625,"orthographic":false}